girder_large_image/__init__.py
girder_large_image/constants.py
girder_large_image/girder_tilesource.py
girder_large_image/loadmodelcache.py
girder_large_image/models/__init__.py
girder_large_image/models/image_item.py
girder_large_image/rest/__init__.py
girder_large_image/rest/item_meta.py
girder_large_image/rest/large_image_resource.py
girder_large_image/rest/tiles.py
girder_large_image/web_client/eventStream.js
girder_large_image/web_client/index.js
girder_large_image/web_client/main.js
girder_large_image/web_client/package.json
girder_large_image/web_client/routes.js
girder_large_image/web_client/webpack.helper.js
girder_large_image/web_client/extra/.gitignore
girder_large_image/web_client/stylesheets/fileList.styl
girder_large_image/web_client/stylesheets/imageViewerSelectWidget.styl
girder_large_image/web_client/stylesheets/itemList.styl
girder_large_image/web_client/stylesheets/itemView.styl
girder_large_image/web_client/stylesheets/itemViewCodemirror.styl
girder_large_image/web_client/stylesheets/largeImageConfig.styl
girder_large_image/web_client/stylesheets/metadataWidget.styl
girder_large_image/web_client/templates/imageViewerSelectWidget.pug
girder_large_image/web_client/templates/itemList.pug
girder_large_image/web_client/templates/itemView.pug
girder_large_image/web_client/templates/itemViewCodemirror.pug
girder_large_image/web_client/templates/largeImageConfig.pug
girder_large_image/web_client/templates/largeImage_fileAction.pug
girder_large_image/web_client/templates/metadataWidget.pug
girder_large_image/web_client/templates/metadatumEditWidget.pug
girder_large_image/web_client/views/configView.js
girder_large_image/web_client/views/fileList.js
girder_large_image/web_client/views/imageViewerSelectWidget.js
girder_large_image/web_client/views/index.js
girder_large_image/web_client/views/itemList.js
girder_large_image/web_client/views/itemView.js
girder_large_image/web_client/views/itemViewCodemirror.js
girder_large_image-1.34.0.dist-info/licenses/LICENSE
girder_large_image-1.34.0.dist-info/METADATA
girder_large_image-1.34.0.dist-info/WHEEL
girder_large_image-1.34.0.dist-info/entry_points.txt
girder_large_image-1.34.0.dist-info/top_level.txt
girder_large_image-1.34.0.dist-info/RECORD
