Metadata-Version: 2.4
Name: girder-large-image
Version: 1.34.0
Summary: A Girder plugin to work with large, multiresolution images.
Home-page: https://github.com/girder/large_image
Author: Kitware, Inc.
Author-email: kitware@kitware.com
License: Apache-2.0
Keywords: girder-plugin,large_image
Classifier: Development Status :: 5 - Production/Stable
Classifier: Programming Language :: Python :: 3
Classifier: Programming Language :: Python :: 3.10
Classifier: Programming Language :: Python :: 3.11
Classifier: Programming Language :: Python :: 3.12
Classifier: Programming Language :: Python :: 3.13
Classifier: Programming Language :: Python :: 3.14
Requires-Python: >=3.10
License-File: LICENSE
Requires-Dist: girder>=3.1.18
Requires-Dist: girder-jobs>=3.0.3
Requires-Dist: large_image>=1.34.0
Provides-Extra: tasks
Requires-Dist: large-image-tasks[girder]>=1.34.0; extra == "tasks"
Requires-Dist: girder-worker[girder]>=0.6.0; extra == "tasks"
Dynamic: author
Dynamic: author-email
Dynamic: classifier
Dynamic: description
Dynamic: description-content-type
Dynamic: home-page
Dynamic: keywords
Dynamic: license
Dynamic: license-file
Dynamic: provides-extra
Dynamic: requires-dist
Dynamic: requires-python
Dynamic: summary
